explain.py
demystify/__init__.py
demystify/__main__.py
demystify/base.py
demystify/buildpuz.py
demystify/config.py
demystify/explain.py
demystify/internal.py
demystify/mus.py
demystify/musdict.py
demystify/musforqes.py
demystify/optux.py
demystify/optuxext.py
demystify/parallel.py
demystify/parse.py
demystify/utils.py
demystify/solvers/pysatimpl.py
demystify/solvers/z3impl.py
demystify-0.0.17.dist-info/LICENSE.txt
demystify-0.0.17.dist-info/METADATA
demystify-0.0.17.dist-info/WHEEL
demystify-0.0.17.dist-info/top_level.txt
demystify-0.0.17.dist-info/RECORD
