Metadata-Version: 2.1
Name: demystify
Version: 0.0.17
Summary: Demystify is a tool which allows puzzles to be expressed in a high-level constraint programming language and uses MUSes to automatically produce descriptions of steps in the puzzle solving.
Home-page: https://github.com/stacs-cp/demystify
Author: Chris Jefferson
Author-email: caj21@st-andrews.ac.uk
License: UNKNOWN
Platform: UNKNOWN
Classifier: License :: OSI Approved :: Mozilla Public License 2.0 (MPL 2.0)
Requires-Dist: python-sat
Requires-Dist: z3-solver
Requires-Dist: numpy
Requires-Dist: sortedcontainers
